vectorgov/__init__.py
vectorgov/_http.py
vectorgov/client.py
vectorgov/config.py
vectorgov/exceptions.py
vectorgov/formatters.py
vectorgov/models.py
vectorgov/integrations/__init__.py
vectorgov/integrations/google_adk.py
vectorgov/integrations/langchain.py
vectorgov/integrations/langgraph.py
vectorgov/integrations/ollama.py
vectorgov/integrations/tools.py
vectorgov/integrations/transformers.py
vectorgov/mcp/__init__.py
vectorgov/mcp/__main__.py
vectorgov/mcp/server.py
vectorgov-0.13.0.dist-info/licenses/LICENSE
vectorgov-0.13.0.dist-info/METADATA
vectorgov-0.13.0.dist-info/WHEEL
vectorgov-0.13.0.dist-info/entry_points.txt
vectorgov-0.13.0.dist-info/top_level.txt
vectorgov-0.13.0.dist-info/RECORD
