Metadata-Version: 2.4
Name: vectorgov
Version: 0.13.0
Summary: SDK Python para acessar bases de conhecimento jurídico VectorGov
Author-email: VectorGov <contato@vectorgov.io>
License: MIT
Project-URL: Homepage, https://vectorgov.io
Project-URL: Documentation, https://vectorgov.io
Project-URL: Repository, https://github.com/euteajudo/vectorgov-sdk
Project-URL: Issues, https://github.com/euteajudo/vectorgov-sdk/issues
Keywords: vectorgov,rag,retrieval,legal,ai,llm
Classifier: Development Status :: 4 - Beta
Classifier: Intended Audience :: Developers
Classifier: License :: OSI Approved :: MIT License
Classifier: Operating System :: OS Independent
Classifier: Programming Language :: Python :: 3
Classifier: Programming Language :: Python :: 3.9
Classifier: Programming Language :: Python :: 3.10
Classifier: Programming Language :: Python :: 3.11
Classifier: Programming Language :: Python :: 3.12
Requires-Python: >=3.9
License-File: LICENSE
Requires-Dist: httpx>=0.24.0
Provides-Extra: dev
Requires-Dist: pytest>=7.0; extra == "dev"
Requires-Dist: pytest-cov>=4.0; extra == "dev"
Requires-Dist: black>=23.0; extra == "dev"
Requires-Dist: ruff>=0.1.0; extra == "dev"
Requires-Dist: mypy>=1.0; extra == "dev"
Provides-Extra: openai
Requires-Dist: openai>=1.0; extra == "openai"
Provides-Extra: anthropic
Requires-Dist: anthropic>=0.18; extra == "anthropic"
Provides-Extra: google
Requires-Dist: google-generativeai>=0.3; extra == "google"
Provides-Extra: langchain
Requires-Dist: langchain>=0.1.0; extra == "langchain"
Requires-Dist: langchain-core>=0.1.0; extra == "langchain"
Provides-Extra: langgraph
Requires-Dist: langgraph>=0.2.0; extra == "langgraph"
Requires-Dist: langchain-core>=0.1.0; extra == "langgraph"
Provides-Extra: google-adk
Requires-Dist: google-adk>=1.0.0; extra == "google-adk"
Provides-Extra: mcp
Requires-Dist: mcp>=1.0.0; extra == "mcp"
Provides-Extra: transformers
Requires-Dist: transformers>=4.35.0; extra == "transformers"
Requires-Dist: torch>=2.0.0; extra == "transformers"
Requires-Dist: accelerate>=0.24.0; extra == "transformers"
Provides-Extra: all
Requires-Dist: openai>=1.0; extra == "all"
Requires-Dist: anthropic>=0.18; extra == "all"
Requires-Dist: google-generativeai>=0.3; extra == "all"
Requires-Dist: langchain>=0.1.0; extra == "all"
Requires-Dist: langchain-core>=0.1.0; extra == "all"
Requires-Dist: langgraph>=0.2.0; extra == "all"
Requires-Dist: google-adk>=1.0.0; extra == "all"
Requires-Dist: mcp>=1.0.0; extra == "all"
Requires-Dist: transformers>=4.35.0; extra == "all"
Requires-Dist: torch>=2.0.0; extra == "all"
Requires-Dist: accelerate>=0.24.0; extra == "all"
Dynamic: license-file
